Metadata-Version: 1.0
Name: binomial-gaussian-dist-fz
Version: 0.1
Summary: Gaussian and Binomial distribution
Home-page: UNKNOWN
Author: UNKNOWN
Author-email: UNKNOWN
License: UNKNOWN
Platform: UNKNOWN
